{
  "CompactFinaliseFor": "101978",
  "CompactFinaliseSelf": "94549",
  "CompactFinaliseTo": "94549",
  "EscrowFinalise": "44316",
  "IntegrationCoinFill": "64965",
  "IntegrationCompactFinaliseSelf": "85359",
  "IntegrationWormholeReceiveMessage": "45665",
  "IntegrationWormholeSubmit": "13837",
  "broadcast": "14904",
  "compactFinaliseSelfWithFee": "164087",
  "depositAndRegisterFor": "129887",
  "escrowFinaliseSelfWithFee": "106519",
  "escrowFinaliseWithSignature": "51505",
  "escrowOpen": "56999",
  "escrowOpenFor3009Single": "85640",
  "escrowOpenFor3009SingleArray": "90796",
  "escrowOpenFor3009Two": "140807",
  "escrowOpenForMsgSender": "57219",
  "escrowOpenForPermit2": "94897"
}